apkutils/__init__.py
apkutils/__main__.py
apkutils/apk.py
apkutils/apkfile.py
apkutils/axml/__init__.py
apkutils/axml/bytecode.py
apkutils/axml/public.py
apkutils/axml/public.xml
apkutils/cert.py
apkutils/cli.py
apkutils/dex/__init__.py
apkutils/dex/byteio.py
apkutils/dex/dalvik.py
apkutils/dex/dalvikformats.py
apkutils/dex/dexparser.py
apkutils/dex/flags.py
apkutils/dex/jvm/__init__.py
apkutils/dex/jvm/arraytypes.py
apkutils/dex/jvm/constantpool.py
apkutils/dex/jvm/constants/__init__.py
apkutils/dex/jvm/constants/calc.py
apkutils/dex/jvm/constants/genlookup.py
apkutils/dex/jvm/constants/lookup.py
apkutils/dex/jvm/error.py
apkutils/dex/jvm/genmathops.py
apkutils/dex/jvm/ir.py
apkutils/dex/jvm/jvmops.py
apkutils/dex/jvm/mathops.py
apkutils/dex/jvm/optimization/__init__.py
apkutils/dex/jvm/optimization/consts.py
apkutils/dex/jvm/optimization/jumps.py
apkutils/dex/jvm/optimization/options.py
apkutils/dex/jvm/optimization/registers.py
apkutils/dex/jvm/optimization/stack.py
apkutils/dex/jvm/scalartypes.py
apkutils/dex/jvm/writebytecode.py
apkutils/dex/jvm/writeclass.py
apkutils/dex/jvm/writeir.py
apkutils/dex/mutf8.py
apkutils/dex/treelist.py
apkutils/dex/typeinference/__init__.py
apkutils/dex/typeinference/typeinference.py
apkutils/dex/util.py
apkutils/elf/__init__.py
apkutils/elf/elfparser.py
apkutils/gdiff.py
apkutils/intersection.py
apkutils/wildcard.py
apkutils-2.0.5.dist-info/WHEEL
apkutils-2.0.5.dist-info/entry_points.txt
apkutils-2.0.5.dist-info/METADATA
apkutils-2.0.5.dist-info/RECORD
