Metadata-Version: 2.3
Name: apkutils
Version: 2.0.5
Summary: 一个APK解析库
Author: kin9-0rz
Author-email: kin9-0rz <kin9-0rz@outlook.com>
Requires-Dist: pygments>=2.12.0,<3.0.0
Requires-Dist: beautifulsoup4>=4.10.0,<5.0.0
Requires-Dist: click>=8.0.3,<9.0.0
Requires-Dist: cryptography>=39.0.1
Requires-Dist: lxml>=5.0.0
Requires-Dist: pyelftools>=0.27,<0.28
Requires-Dist: pyftype>=1.2.4,<2.0.0
Requires-Dist: colorlog>=6.7.0,<7.0.0
Requires-Python: >=3.10
Project-URL: Repository, https://gitee.com/kin9-0rz/apkutils
